tlfp/__init__.py
tlfp/format_data_for_frontend.py
tlfp/generate_dossiers_csv.py
tlfp/merge.py
tlfp/parse_doslegs_texts.py
tlfp/parse_one.py
tlfp/tools/__init__.py
tlfp/tools/_step_logic.py
tlfp/tools/add_links.py
tlfp/tools/assemble_procedures.py
tlfp/tools/common.py
tlfp/tools/compare_all_thelawfactory_and_me.py
tlfp/tools/complete_articles.py
tlfp/tools/compute_stats.py
tlfp/tools/detect_anomalies.py
tlfp/tools/download_AN_opendata.py
tlfp/tools/download_groupes.py
tlfp/tools/download_lois_dites.py
tlfp/tools/json2arbo.py
tlfp/tools/make_git_repos.py
tlfp/tools/make_metrics_csv.py
tlfp/tools/parse_texte.py
tlfp/tools/prepare_amendements.py
tlfp/tools/prepare_articles.py
tlfp/tools/prepare_interventions.py
tlfp/tools/process_conscons.py
tlfp/tools/process_jo.py
tlfp/tools/reorder_interventions_and_correct_procedure.py
tlfp/tools/sort_articles.py
tlfp/tools/steps_as_dot.py
tlfp/tools/update_procedure.py
tlfp/tools/valid_procedure.json
tlfp-0.0.3.data/scripts/tlfp-parse
tlfp-0.0.3.data/scripts/tlfp-parse-many
tlfp-0.0.3.data/scripts/tlfp-parse-text
tlfp-0.0.3.dist-info/LICENSE
tlfp-0.0.3.dist-info/METADATA
tlfp-0.0.3.dist-info/WHEEL
tlfp-0.0.3.dist-info/top_level.txt
tlfp-0.0.3.dist-info/RECORD
