Metadata-Version: 2.1
Name: tlfp
Version: 0.0.3
Summary: Data generator for the-law-factory project lafabriquedelaloi.fr
Home-page: https://github.com/regardscitoyens/the-law-factory-parser
Author: Regards Citoyens
Author-email: contact@regardscitoyens.org
License: GPL
Keywords: scraping politics data
Platform: UNKNOWN
Classifier: Development Status :: 1 - Planning
Classifier: License :: OSI Approved :: GNU General Public License (GPL)
Classifier: Operating System :: OS Independent
Classifier: Programming Language :: Python :: 3
Classifier: Programming Language :: Python :: 3.5
Classifier: Programming Language :: Python :: 3.6
Classifier: Programming Language :: Python :: Implementation :: PyPy
Requires-Dist: lawfactory-utils
Requires-Dist: anpy (==0.1.22)
Requires-Dist: legipy (==0.1.2)
Requires-Dist: senapy (==0.2.15)
Requires-Dist: metslesliens (==1.3.0)
Requires-Dist: diff-match-patch (==20121119)
Requires-Dist: python-gitlab (==1.5.1)
